plone.browserlayer-3.0.2-py3.11-nspkg.pth
plone/browserlayer/README.rst
plone/browserlayer/__init__.py
plone/browserlayer/configure.zcml
plone/browserlayer/exportimport.py
plone/browserlayer/interfaces.py
plone/browserlayer/layer.py
plone/browserlayer/testing.py
plone/browserlayer/utils.py
plone/browserlayer/tests/__init__.py
plone/browserlayer/tests/interfaces.py
plone/browserlayer/tests/local.pt
plone/browserlayer/tests/standard.pt
plone/browserlayer/tests/test_doctest.py
plone/browserlayer/tests/testing.zcml
plone/browserlayer/tests/profiles/testing/browserlayer.xml
plone/browserlayer/tests/profiles/uninstall/browserlayer.xml
plone.browserlayer-3.0.2.dist-info/METADATA
plone.browserlayer-3.0.2.dist-info/WHEEL
plone.browserlayer-3.0.2.dist-info/namespace_packages.txt
plone.browserlayer-3.0.2.dist-info/top_level.txt
plone.browserlayer-3.0.2.dist-info/RECORD
